Metadata-Version: 1.1
Name: PyLyrics
Version: 1.0.0
Summary: Pythonic Implementation of lyrics.wikia.com
Home-page: http://github.com/geekpradd/PyLyrics
Author: Pradipta Bora
Author-email: pradd@outlook.com
License: MIT
Platform: UNKNOWN
Classifier: Development Status :: 5 - Production/Stable
Classifier: Topic :: Internet
Classifier: License :: OSI Approved :: MIT License
Classifier: Operating System :: OS Independent
Classifier: Programming Language :: Python
